duckpy/__init__.py
duckpy/types.py
duckpy/aio/__init__.py
duckpy-3.2.0.dist-info/LICENSE
duckpy-3.2.0.dist-info/METADATA
duckpy-3.2.0.dist-info/WHEEL
duckpy-3.2.0.dist-info/top_level.txt
duckpy-3.2.0.dist-info/RECORD
