Metadata-Version: 2.1
Name: duckpy
Version: 3.2.0
Summary: A simple module for searching on DuckDuckGo
Home-page: https://github.com/AmanoTeam/duckpy
Author: Amano Team
Author-email: contact@amanoteam.com
License: MIT
Platform: UNKNOWN
Requires-Python: >=3.6
Requires-Dist: beautifulsoup4 (>=4.9.1)
Requires-Dist: httpx[http2] (<0.19,>=0.14)
